epimetheus_py-0.7.7.dist-info/METADATA
epimetheus_py-0.7.7.dist-info/WHEEL
epymetheus/__init__.py
epymetheus/epymetheus.cpython-39-x86_64-linux-gnu.so
epimetheus_py-0.7.7.dist-info/RECORD
