Metadata-Version: 2.4
Name: epimetheus_py
Version: 0.7.7
Classifier: Programming Language :: Rust
Requires-Dist: polars
Requires-Dist: pyarrow
Requires-Dist: pytest>=8 ; extra == 'testing'
Requires-Dist: biopython ; extra == 'testing'
Provides-Extra: testing
Author-email: Sebastian Dall <semoda@bio.aau.dk>
